libbids/__init__.py
libbids/clibbids.cpython-310-darwin.so
libbids/dataset.py
libbids/enums.py
libbids/event.py
libbids/notes.py
libbids/run.py
libbids/task.py
libbids/utils.py
libbids/instruments/__init__.py
libbids/instruments/eeg_instrument.py
libbids/instruments/ieeg_instrument.py
libbids/instruments/instrument.py
libbids/instruments/physio_instrument.py
libbids/instruments/read_instrument.py
libbids/instruments/stim_instrument.py
libbids/instruments/write_instrument.py
libbids-0.2.0.dist-info/METADATA
libbids-0.2.0.dist-info/WHEEL
libbids-0.2.0.dist-info/top_level.txt
libbids-0.2.0.dist-info/RECORD
